{
  "metadata": {
    "date": "2026-04-23",
    "language": "c",
    "total_repositories": 19,
    "total_stars": 294151,
    "total_forks": 85427,
    "generated_by": "GitHub Trending Scraper",
    "format_version": "1.0"
  },
  "repositories": [
    {
      "rank": 1,
      "name": "lvgl/lvgl",
      "url": "https://github.com/lvgl/lvgl",
      "description": "Embedded graphics library to create beautiful UIs for any MCU, MPU and display type.",
      "language": "C",
      "stars": 23341,
      "forks": 4131,
      "stars_today": "13 stars today",
      "built_by": [
        "kisvegabor",
        "embeddedt",
        "FASTSHIFT",
        "github-actions",
        "W-Mai"
      ]
    },
    {
      "rank": 2,
      "name": "pbatard/rufus",
      "url": "https://github.com/pbatard/rufus",
      "description": "The Reliable USB Formatting Utility",
      "language": "C",
      "stars": 35619,
      "forks": 3020,
      "stars_today": "51 stars today",
      "built_by": [
        "pbatard",
        "bovirus",
        "ThiloL",
        "MehmetaliKuran",
        "Sopor"
      ]
    },
    {
      "rank": 3,
      "name": "espressif/esp-idf",
      "url": "https://github.com/espressif/esp-idf",
      "description": "Espressif IoT Development Framework. Official development framework for Espressif SoCs.",
      "language": "C",
      "stars": 17879,
      "forks": 8228,
      "stars_today": "7 stars today",
      "built_by": [
        "igrr",
        "projectgus",
        "jack0c",
        "suda-morris",
        "mahavirj"
      ]
    },
    {
      "rank": 4,
      "name": "lightpanda-io/browser",
      "url": "https://github.com/lightpanda-io/browser",
      "description": "Lightpanda: the headless browser designed for AI and automation",
      "language": "Zig",
      "stars": 29161,
      "forks": 1255,
      "stars_today": "89 stars today",
      "built_by": [
        "karlseguin",
        "krichprollsch",
        "francisbouvier",
        "mookums",
        "arrufat"
      ]
    },
    {
      "rank": 5,
      "name": "qmk/qmk_firmware",
      "url": "https://github.com/qmk/qmk_firmware",
      "description": "Open-source keyboard firmware for Atmel AVR and Arm USB families",
      "language": "C",
      "stars": 20304,
      "forks": 43796,
      "stars_today": "2 stars today",
      "built_by": [
        "fauxpark",
        "qmk-bot",
        "drashna",
        "noroadsleft",
        "zvecr"
      ]
    },
    {
      "rank": 6,
      "name": "timescale/timescaledb",
      "url": "https://github.com/timescale/timescaledb",
      "description": "A time-series database for high-performance real-time analytics packaged as a Postgres extension",
      "language": "C",
      "stars": 22465,
      "forks": 1080,
      "stars_today": "9 stars today",
      "built_by": [
        "svenklemm",
        "erimatnor",
        "cevian",
        "mkindahl",
        "akuzm"
      ]
    },
    {
      "rank": 7,
      "name": "vedderb/bldc",
      "url": "https://github.com/vedderb/bldc",
      "description": "The VESC motor control firmware",
      "language": "C",
      "stars": 3077,
      "forks": 1771,
      "stars_today": "5 stars today",
      "built_by": [
        "vedderb",
        "Mitchlol",
        "nitrousnrg",
        "kubark42",
        "Jfriesen222"
      ]
    },
    {
      "rank": 8,
      "name": "DarkFlippers/unleashed-firmware",
      "url": "https://github.com/DarkFlippers/unleashed-firmware",
      "description": "Flipper Zero Unleashed Firmware",
      "language": "C",
      "stars": 21448,
      "forks": 1861,
      "stars_today": "10 stars today",
      "built_by": [
        "xMasterX",
        "skotopes",
        "hedger",
        "gornekich",
        "DrZlo13"
      ]
    },
    {
      "rank": 9,
      "name": "Cisco-Talos/clamav",
      "url": "https://github.com/Cisco-Talos/clamav",
      "description": "ClamAV - Documentation is here: https://docs.clamav.net",
      "language": "C",
      "stars": 6536,
      "forks": 849,
      "stars_today": "6 stars today",
      "built_by": [
        "val-ms",
        "Emzi-Noxum",
        "TheRaynMan",
        "recvfrom",
        "steve-morgan"
      ]
    },
    {
      "rank": 10,
      "name": "hathach/tinyusb",
      "url": "https://github.com/hathach/tinyusb",
      "description": "An open source cross-platform USB stack for embedded system",
      "language": "C",
      "stars": 6734,
      "forks": 1406,
      "stars_today": "4 stars today",
      "built_by": [
        "hathach",
        "HiFiPhile",
        "pigrew",
        "kkitayam",
        "cr1901"
      ]
    },
    {
      "rank": 11,
      "name": "jqlang/jq",
      "url": "https://github.com/jqlang/jq",
      "description": "Command-line JSON processor",
      "language": "C",
      "stars": 34528,
      "forks": 1764,
      "stars_today": "16 stars today",
      "built_by": [
        "stedolan",
        "nicowilliams",
        "itchyny",
        "dtolnay",
        "github-actions"
      ]
    },
    {
      "rank": 12,
      "name": "raspberrypi/linux",
      "url": "https://github.com/raspberrypi/linux",
      "description": "Kernel source tree for Raspberry Pi-provided kernel builds. Issues unrelated to the linux kernel should be posted on the community forum at https://forums.raspberrypi.com/",
      "language": "C",
      "stars": 12791,
      "forks": 5397,
      "stars_today": "4 stars today",
      "built_by": [
        "torvalds",
        "davem330",
        "arndb",
        "broonie",
        "tiwai"
      ]
    },
    {
      "rank": 13,
      "name": "freebsd/freebsd-src",
      "url": "https://github.com/freebsd/freebsd-src",
      "description": "The FreeBSD src tree publish-only repository. Experimenting with 'simple' pull requests....",
      "language": "C",
      "stars": 9035,
      "forks": 3272,
      "stars_today": "4 stars today",
      "built_by": [
        "bsdimp",
        "bsdjhb",
        "kostikbel",
        "bsdphk",
        "DarkHelmet433"
      ]
    },
    {
      "rank": 14,
      "name": "signalwire/freeswitch",
      "url": "https://github.com/signalwire/freeswitch",
      "description": "FreeSWITCH is a Software Defined Telecom Stack enabling the digital transformation from proprietary telecom switches to a versatile software implementation that runs on any commodity hardware. From a Raspberry PI to a multi-core server, FreeSWITCH can unlock the telecommunications potential of any device.",
      "language": "C",
      "stars": 4810,
      "forks": 1756,
      "stars_today": "3 stars today",
      "built_by": [
        "anthmFS",
        "mjerris",
        "briankwest",
        "andywolk",
        "seven1240"
      ]
    },
    {
      "rank": 15,
      "name": "pgvector/pgvector",
      "url": "https://github.com/pgvector/pgvector",
      "description": "Open-source vector similarity search for Postgres",
      "language": "C",
      "stars": 20943,
      "forks": 1151,
      "stars_today": "21 stars today",
      "built_by": [
        "ankane",
        "hlinnaka",
        "jkatz",
        "lychen0618",
        "binarycleric"
      ]
    },
    {
      "rank": 16,
      "name": "apache/nuttx",
      "url": "https://github.com/apache/nuttx",
      "description": "Apache NuttX is a mature, real-time embedded operating system (RTOS)",
      "language": "C",
      "stars": 3819,
      "forks": 1556,
      "stars_today": "3 stars today",
      "built_by": [
        "gregory-nutt",
        "xiaoxiang781216",
        "yamt",
        "anchao",
        "raiden00pl"
      ]
    },
    {
      "rank": 17,
      "name": "Zaneham/BarraCUDA",
      "url": "https://github.com/Zaneham/BarraCUDA",
      "description": "Open-source CUDA compiler targeting multiple GPU architectures. Compiles .cu to AMD and Tenstorrent GPU's",
      "language": "C",
      "stars": 1653,
      "forks": 81,
      "stars_today": "7 stars today",
      "built_by": [
        "Zaneham",
        "nataliakokoromyti"
      ]
    },
    {
      "rank": 18,
      "name": "reactos/reactos",
      "url": "https://github.com/reactos/reactos",
      "description": "A free Windows-compatible Operating System",
      "language": "C",
      "stars": 17421,
      "forks": 2099,
      "stars_today": "5 stars today",
      "built_by": [
        "AmineKhaldi",
        "tkreuzer",
        "EricKohl",
        "HBelusca",
        "ThFabba"
      ]
    },
    {
      "rank": 19,
      "name": "pjsip/pjproject",
      "url": "https://github.com/pjsip/pjproject",
      "description": "PJSIP project",
      "language": "C",
      "stars": 2587,
      "forks": 954,
      "stars_today": "4 stars today",
      "built_by": [
        "bennylp",
        "nanangizz",
        "sauwming",
        "trengginas",
        "jimying"
      ]
    }
  ]
}